__init__.py
evaluation.py
imputers/__init__.py
imputers/locf.py
imputers/median.py
imputers/mice_3d.py
mice3d-0.1.0.dist-info/licenses/LICENSE
mice3d-0.1.0.dist-info/METADATA
mice3d-0.1.0.dist-info/WHEEL
mice3d-0.1.0.dist-info/top_level.txt
mice3d-0.1.0.dist-info/RECORD
