Metadata-Version: 2.4
Name: mice3d
Version: 0.1.0
Summary: Add your description here
Requires-Python: >=3.11
License-File: LICENSE
Requires-Dist: matplotlib>=3.10.8
Requires-Dist: numpy>=2.4.2
Requires-Dist: pandas>=3.0.0
Requires-Dist: scikit-learn>=1.8.0
Requires-Dist: tabulate>=0.9.0
Dynamic: license-file
